setup.cfg
setup.py
ezplone/__init__.py
ezplone/init.py
ezplone/inst.py
ezplone/prop.py
ezplone/utils.py
ezplone.egg-info/PKG-INFO
ezplone.egg-info/SOURCES.txt
ezplone.egg-info/dependency_links.txt
ezplone.egg-info/entry_points.txt
ezplone.egg-info/not-zip-safe
ezplone.egg-info/requires.txt
ezplone.egg-info/top_level.txt