Metadata-Version: 1.0
Name: ezplone
Version: 0.3
Summary: Simple utilties for Plone product initilisation and installation.
Home-page: http://www.agapow.net/software/ezplone
Author: Paul-Michael Agapow
Author-email: agapow@bbsrc.ac.uk
License: BSD
Keywords: plone install product utilities debug
Platform: UNKNOWN
Classifier: Framework :: Plone
Classifier: Programming Language :: Python
Classifier: Topic :: Software Development :: Libraries :: Python Modules
Classifier: Development Status :: 4 - Beta
Classifier: License :: OSI Approved :: BSD License
